walax/__init__.py
walax/admin.py
walax/apps.py
walax/decorators.py
walax/metadata.py
walax/models.py
walax/routers.py
walax/serializers.py
walax/tests.py
walax/views.py
walax-1.1.5.dist-info/LICENSE
walax-1.1.5.dist-info/METADATA
walax-1.1.5.dist-info/WHEEL
walax-1.1.5.dist-info/top_level.txt
walax-1.1.5.dist-info/RECORD
