Metadata-Version: 2.1
Name: walax
Version: 1.1.5
Summary: Walax Django API
Home-page: https://github.com/hazelmollusk/django-walax
Author: Matt Barry
Author-email: matt@hazelmollusk.org
License: UNKNOWN
Project-URL: Bug Tracker, https://github.com/pypa/sampleproject/issues
Platform: UNKNOWN
Classifier: Programming Language :: Python :: 3
Classifier: License :: OSI Approved :: MIT License
Classifier: Operating System :: OS Independent
Requires-Python: >=3.6
License-File: LICENSE
